PhenGO/PhenGO.py
PhenGO/__init__.py
PhenGO/compare_arff_genes.py
PhenGO/constants.py
PhenGO/fly_pheno_summary.py
PhenGO/go_handling.py
PhenGO/obo_to_graph.py
PhenGO/phenotype_handling.py
PhenGO/data/__init__.py
PhenGO/data/fly/__init__.py
PhenGO/data/mouse/__init__.py
PhenGO/data/worm/__init__.py
phengo-0.1.2.dist-info/licenses/LICENSE
phengo-0.1.2.dist-info/METADATA
phengo-0.1.2.dist-info/WHEEL
phengo-0.1.2.dist-info/entry_points.txt
phengo-0.1.2.dist-info/top_level.txt
phengo-0.1.2.dist-info/RECORD
