Metadata-Version: 2.4
Name: PhenGO
Version: 0.1.2
Summary: PhenoGO: A tool to build WEKA-ready ARFF files from model organism phenotype and Gene Ontology (GO) annotations.
Home-page: https://github.com/NickJD/PhenoGO
Author: Nicholas Dimonaco
Author-email: nicholas@dimonaco.co.uk
Project-URL: Bug Tracker, https://github.com/NickJD/PhenoGO/issues
Keywords: phenotype,gene ontology,GO,WEKA,ARFF,machine learning,model organism
Classifier: Programming Language :: Python :: 3
Classifier: License :: OSI Approved :: GNU General Public License v3 (GPLv3)
Classifier: Operating System :: OS Independent
Requires-Python: >=3.6
License-File: LICENSE
Requires-Dist: networkx
Dynamic: license-file
